radifox/qa/__init__.py
radifox/qa/_static_version.py
radifox/qa/_version.py
radifox/qa/app.py
radifox/qa/run.py
radifox/qa/templates/conversion.html
radifox/qa/templates/index.html
radifox/qa/templates/login.html
radifox/qa/templates/processing.html
radifox/qa/templates/project.html
radifox/qa/templates/subject.html
radifox_qa-1.0.1.dist-info/LICENSE
radifox_qa-1.0.1.dist-info/METADATA
radifox_qa-1.0.1.dist-info/WHEEL
radifox_qa-1.0.1.dist-info/entry_points.txt
radifox_qa-1.0.1.dist-info/top_level.txt
radifox_qa-1.0.1.dist-info/RECORD
