Metadata-Version: 2.1
Name: radifox-qa
Version: 1.0.1
Summary: A quality assurance webapp for the RADIFOX framework.
Author-email: JH-MIPC <jhmipc@jh.edu>
License: Apache-2.0
Project-URL: Homepage, https://github.com/jh-mipc/radifox-qa
Classifier: Programming Language :: Python :: 3
Classifier: License :: OSI Approved :: Apache Software License
Classifier: Operating System :: OS Independent
Requires-Python: >=3.7
License-File: LICENSE
Requires-Dist: flask
Requires-Dist: gunicorn
Requires-Dist: pyyaml
Requires-Dist: radifox >=2.1.0
